pyconv/__init__.py
pyconv/pyconv.py
pyconv/pyconv_calc.py
convpy-0.9.1.dist-info/LICENSE
convpy-0.9.1.dist-info/METADATA
convpy-0.9.1.dist-info/WHEEL
convpy-0.9.1.dist-info/entry_points.txt
convpy-0.9.1.dist-info/top_level.txt
convpy-0.9.1.dist-info/RECORD
