Metadata-Version: 2.1
Name: convpy
Version: 0.9.1
Summary: CLI base number type converter
Author-email: Simon Crampton <simongc100@gmail.com>
License: GPL-3.0
Project-URL: Repository, https://github.com/DragonSGC/pyconv
Keywords: cli,convertor,binary,octal,decimal,hexidecimal
Classifier: Development Status :: 4 - Beta
Classifier: Programming Language :: Python :: 3
Classifier: License :: OSI Approved :: GNU General Public License v3 (GPLv3)
Classifier: Operating System :: OS Independent
Requires-Python: >=3.10
License-File: LICENSE
Requires-Dist: click
Provides-Extra: dev
Requires-Dist: pytest ; extra == 'dev'
Requires-Dist: black ; extra == 'dev'
Requires-Dist: flake8 ; extra == 'dev'
